Workbook

Sheet Read Me
A1: Investor Readiness Engine — Synthetic Data Workbook
A3: Purpose | B3: Synthetic workbook for the earnings-call readiness prototype.
A4: Latest quarter | B4: Q2 FY25
A5: Data type | B5: Fully synthetic; created for examination/demo purposes.
A6: Core scenario | B6: Revenue grows strongly; operating margin falls; cash flow weakens; segment performance diverges; prior commitments are tested.
A7: Key assumption | B7: Segment revenue is shown before group-level inter-segment eliminations; consolidated revenue is the primary company-level metric.
A9: Key Synthetic Assumptions
A10: Assumption | B10: Detail
A11: Currency | B11: ₹ crore
A12: Consolidated revenue | B12: Primary company-level revenue metric.
A13: Segment revenue | B13: Pre-elimination segment revenue; Q1 FY25 contains ₹34 Cr of group-level eliminations to reconcile to consolidated revenue.
A14: Management commentary | B14: Synthetic statements designed to explain the case signals.
A15: Historical guidance | B15: Synthetic commitments designed to create measurable guidance gaps.

Sheet Quarterly Financials
A1: Quarterly Financial Results
A3: Metric | B3: Q3 FY24 | C3: Q4 FY24 | D3: Q1 FY25 | E3: Q2 FY25 | F3: QoQ Change | G3: Change vs Q3 FY24 | H3: Source / Assumption | I3: Units | J3: Type | K3: Latest-quarter interpretation
A4: Revenue | B4: 820 | C4: 900 | D4: 1000 | E4: 1150 | F4: =E4/D4-1 -> 0.15 | G4: =E4/B4-1 -> 0.40243902 | H4: Synthetic case assumption | I4: ₹ Cr | J4: Input | K4: Strong growth
A5: Operating Profit | B5: 164 | C5: 198 | D5: 220 | E5: 207 | F5: =E5/D5-1 -> -0.059090909 | G5: =E5/B5-1 -> 0.26219512 | H5: Synthetic case assumption | I5: ₹ Cr | J5: Input | K5: Profit declines despite revenue growth
A6: Operating Margin | B6: =B5/B4 -> 0.2 | C6: =C5/C4 -> 0.22 | D6: =D5/D4 -> 0.22 | E6: =E5/E4 -> 0.18 | F6: =E6-D6 -> -0.04 | G6: =E6-B6 -> -0.02 | H6: Calculated from Revenue and Operating Profit | I6: % | J6: Formula | K6: Material margin compression
A7: Operating Cash Flow | B7: 140 | C7: 180 | D7: 150 | E7: 110 | F7: =E7/D7-1 -> -0.26666667 | G7: =E7/B7-1 -> -0.21428571 | H7: Synthetic case assumption | I7: ₹ Cr | J7: Input | K7: Cash generation weakened
A10: Supporting Financial Metrics
A11: Metric | B11: Q3 FY24 | C11: Q4 FY24 | D11: Q1 FY25 | E11: Q2 FY25 | F11: QoQ Change | G11: Source / Assumption | H11: Interpretation
A12: Capital Expenditure | B12: 90 | C12: 95 | D12: 110 | E12: 120 | F12: =E12/D12-1 -> 0.090909091 | G12: Synthetic case assumption | H12: Investment increased
A13: Receivables | B13: 210 | C13: 225 | D13: 260 | E13: 320 | F13: =E13/D13-1 -> 0.23076923 | G13: Synthetic case assumption | H13: Receivables increased materially
A14: Inventory | B14: 160 | C14: 170 | D14: 175 | E14: 190 | F14: =E14/D14-1 -> 0.085714286 | G14: Synthetic case assumption | H14: Inventory increased
A15: Working Capital Proxy | B15: =B13+B14 -> 370 | C15: =C13+C14 -> 395 | D15: =D13+D14 -> 435 | E15: =E13+E14 -> 510 | F15: =E15-D15 -> 75 | G15: Receivables + Inventory; illustrative proxy | H15: Working-capital absorption increased
A16: Free Cash Flow | B16: =B7-B12 -> 50 | C16: =C7-C12 -> 85 | D16: =D7-D12 -> 40 | E16: =E7-E12 -> -10 | F16: =E16-D16 -> -50 | G16: Operating Cash Flow - Capital Expenditure | H16: Negative in latest quarter
A18: Comparison note: Q2 FY25 operating cash flow is ₹110 Cr versus ₹180 Cr in Q4 FY24, a 38.9% decline across that comparison window. Quarter-on-quarter from Q1 FY25 to Q2 FY25, the decline is 26.7%. The prototype should always label the comparison period.

Sheet Segment Data
A1: Segment Performance Analysis
A3: Segment | B3: Q3 FY24 Revenue | C3: Q4 FY24 Revenue | D3: Q1 FY25 Revenue | E3: Q2 FY25 Revenue | F3: Q2 QoQ Growth | G3: Previous Growth | H3: Growth Change | I3: Q2 Margin | J3: Revenue Contribution | K3: Trend | L3: Investor Concern
A4: Enterprise Solutions | B4: 360 | C4: 390 | D4: 417 | E4: 500 | F4: =E4/D4-1 -> 0.19904077 | G4: =D4/C4-1 -> 0.069230769 | H4: =F4-G4 -> 0.12981 | I4: 0.22 | J4: =E4/'Quarterly Financials'!$E$4 -> 0.43478261 | K4: Strong | L4: Acceleration supports overall growth
A5: Consumer Technology | B5: 300 | C5: 330 | D5: 364 | E5: 389 | F5: =E5/D5-1 -> 0.068681319 | G5: =D5/C5-1 -> 0.1030303 | H5: =F5-G5 -> -0.034348984 | I5: 0.15 | J5: =E5/'Quarterly Financials'!$E$4 -> 0.33826087 | K5: Slowing | L5: Growth slowed materially from prior quarter
A6: Digital Services | B6: 130 | C6: 150 | D6: 253 | E6: 261 | F6: =E6/D6-1 -> 0.031620553 | G6: =D6/C6-1 -> 0.68666667 | H6: =F6-G6 -> -0.65504611 | I6: 0.18 | J6: =E6/'Quarterly Financials'!$E$4 -> 0.22695652 | K6: Weak | L6: Growth remains low relative to the portfolio
A7: Other / Inter-segment eliminations | B7: 30 | C7: 30 | D7: -34 | E7: 0 | F7: =E7/D7-1 -> -1 | G7: =D7/C7-1 -> -2.1333333 | H7: =F7-G7 -> 1.1333333 | J7: =E7/'Quarterly Financials'!$E$4 -> 0 | K7: Neutral | L7: Used to reconcile gross segment presentation to consolidated revenue
A8: Total / Reconciliation | B8: =SUM(B4:B7) -> 820 | C8: =SUM(C4:C7) -> 900 | D8: =SUM(D4:D7) -> 1000 | E8: =SUM(E4:E7) -> 1150 | F8: =E8/D8-1 -> 0.15 | G8: =D8/C8-1 -> 0.11111111 | H8: =F8-G8 -> 0.038888889 | J8: =E8/'Quarterly Financials'!$E$4 -> 1 | K8: Reference | L8: Consolidated revenue remains the primary company-level metric

Sheet Management Commitments
A1: Management Commitments vs Actuals
A3: Quarter | B3: Management Statement | C3: Metric | D3: Expected Value | E3: Actual Q2 FY25 | F3: Gap | G3: Status | H3: Supporting Evidence | I3: Source / Assumption | J3: Investor Implication
A4: Q4 FY24 | B4: We expect operating margin to remain above 20% over the coming quarters. | C4: Operating Margin | D4: >20% | E4: ='Quarterly Financials'!E6 -> 0.18 | F4: =E4-0.2 -> -0.02 | G4: =IF(E4>0.2,"Missed",IF(E4=0.2,"Met","Missed")) -> Missed | H4: Q2 FY25 actual margin is 18%. | I4: Synthetic previous earnings-call statement | J4: Credibility and profitability question
A5: Q4 FY24 | B5: We expect operating cash-flow conversion to improve as working-capital normalization progresses. | C5: Operating Cash Flow | D5: Improve | E5: ='Quarterly Financials'!E7 -> 110 | F5: =E5-180 -> -70 | G5: =IF(E5>=180,"Met","Missed") -> Missed | H5: Q2 FY25 operating cash flow is ₹110 Cr versus ₹180 Cr in Q4 FY24. | I5: Synthetic previous earnings-call statement | J5: Cash conversion concern
A6: Q4 FY24 | B6: We expect Consumer Technology growth to remain in the low double digits. | C6: Segment Growth | D6: 10%–15% | E6: ='Segment Data'!F5 -> 0.068681319 | F6: =E6-0.1 -> -0.031318681 | G6: =IF(E6>=0.1,"Met",IF(E6>=0.08,"Partially Met","Missed")) -> Missed | H6: Q2 FY25 growth is approximately 7.1%. | I6: Synthetic previous earnings-call statement | J6: Demand / segment slowdown concern
A7: Q4 FY24 | B7: We expect overall revenue growth to remain in the mid-teens. | C7: Revenue Growth | D7: 13%–17% | E7: ='Quarterly Financials'!F4 -> 0.15 | F7: =E7-0.13 -> 0.02 | G7: =IF(AND(E7>=0.13,E7<=0.17),"Met","Missed") -> Met | H7: Q2 FY25 revenue growth is 15.0% quarter-on-quarter. | I7: Synthetic previous earnings-call statement | J7: Commitment met

Sheet Management Commentary
A1: Synthetic Q2 FY25 Management Commentary
A3: Theme | B3: Synthetic Management Commentary | C3: Evidence / Metric | D3: Investor Relevance
A4: Higher input costs | B4: Input and supplier costs increased during the quarter, putting pressure on operating profitability. | C4: ~8% increase in input / supplier costs | D4: Explains part of margin compression
A5: Unfavourable product mix | B5: Revenue growth was concentrated in lower-margin offerings, reducing the benefit of topline growth on profitability. | C5: Operating margin fell to 18% | D5: Raises earnings-quality concern
A6: Consumer Technology slowdown | B6: Demand softened in selected consumer categories, resulting in slower growth in Consumer Technology. | C6: Segment growth ~7% versus ~15% previously | D6: Raises segment-growth concern
A7: Working-capital movement | B7: Higher receivables and inventory absorbed cash during the quarter despite revenue growth. | C7: Receivables ₹320 Cr; inventory ₹190 Cr | D7: Explains weak operating cash flow
A8: Management actions | B8: Management initiated pricing actions, supplier negotiations and cost-efficiency initiatives to improve margins and cash conversion. | C8: Actions disclosed for next quarters | D8: Provides basis for response
A9: Outlook | B9: Management expects margin pressure to moderate as pricing actions and cost initiatives are implemented, subject to market and input-cost conditions. | C9: Forward-looking statement | D9: Needs careful wording in earnings call

Sheet Investor Risk Map
A1: Investor Risk Map
A3: Issue | B3: What Changed? | C3: Why It Matters | D3: Financial Impact (1–5) | E3: Negative Trend (1–5) | F3: Guidance Gap (1–5) | G3: Strategic Importance (1–5) | H3: Total Score | I3: Risk Level | J3: Preparation Need
A4: Operating margin decline | B4: 22% → 18% | C4: Revenue growth is not translating into profitability. | D4: 5 | E4: 5 | F4: 5 | G4: 4 | H4: =SUM(D4:G4) -> 19 | I4: =IF(H4>=16,"Critical",IF(H4>=11,"High",IF(H4>=6,"Moderate","Low"))) -> Critical | J4: Prepare quantified margin bridge and acknowledge guidance gap.
A5: Cash-flow deterioration | B5: ₹180 Cr → ₹110 Cr versus Q4 FY24 | C5: Weak cash conversion can challenge earnings quality. | D5: 5 | E5: 5 | F5: 4 | G5: 4 | H5: =SUM(D5:G5) -> 18 | I5: =IF(H5>=16,"Critical",IF(H5>=11,"High",IF(H5>=6,"Moderate","Low"))) -> Critical | J5: Explain receivables, inventory and normalization actions.
A6: Consumer Technology slowdown | B6: ~15% → ~7% growth | C6: Demand weakness could affect future growth mix. | D6: 3 | E6: 4 | F6: 3 | G6: 4 | H6: =SUM(D6:G6) -> 14 | I6: =IF(H6>=16,"Critical",IF(H6>=11,"High",IF(H6>=6,"Moderate","Low"))) -> High | J6: Prepare segment recovery / demand response.
A7: Guidance miss (margin) | B7: Expected >20%; actual 18% | C7: Raises management credibility concern. | D7: 4 | E7: 4 | F7: 5 | G7: 4 | H7: =SUM(D7:G7) -> 17 | I7: =IF(H7>=16,"Critical",IF(H7>=11,"High",IF(H7>=6,"Moderate","Low"))) -> Critical | J7: Directly acknowledge prior commitment and explain deviation.
A8: Working-capital pressure | B8: Receivables and inventory increased | C8: Cash generation weakened despite revenue growth. | D8: 4 | E8: 4 | F8: 2 | G8: 3 | H8: =SUM(D8:G8) -> 13 | I8: =IF(H8>=16,"Critical",IF(H8>=11,"High",IF(H8>=6,"Moderate","Low"))) -> High | J8: Prepare cash conversion bridge.
A9: Digital Services slowdown | B9: ~8% → ~3% growth | C9: Raises sustainability question. | D9: 3 | E9: 3 | F9: 2 | G9: 3 | H9: =SUM(D9:G9) -> 11 | I9: =IF(H9>=16,"Critical",IF(H9>=11,"High",IF(H9>=6,"Moderate","Low"))) -> High | J9: Explain pipeline and demand drivers using disclosed evidence.
A10: Revenue quality | B10: Topline +15%; margin -4 percentage points | C10: Investors may challenge quality of growth. | D10: 4 | E10: 4 | F10: 4 | G10: 4 | H10: =SUM(D10:G10) -> 16 | I10: =IF(H10>=16,"Critical",IF(H10>=11,"High",IF(H10>=6,"Moderate","Low"))) -> Critical | J10: Prepare mix and margin explanation.

Sheet Investor Questions
A1: Top Investor Questions
A3: Priority | B3: Category | C3: Investor Question | D3: Why Investor Would Ask | E3: Key Evidence | F3: Previous Commitment | G3: Risk Level | H3: Recommended Preparation
A4: 1 | B4: Profitability | C4: Revenue grew by 15%, so why did operating margin fall from 22% to 18%? | D4: Strong topline growth has not translated into profitability. | E4: Revenue +15%; margin -4 percentage points; input costs ~+8%; lower-margin mix. | F4: Margin expected to remain above 20%. | G4: Critical | H4: Prepare quantified margin bridge; acknowledge guidance miss.
A5: 2 | B5: Cash Flow | C5: Why did operating cash flow decline despite strong revenue growth? | D5: Investors may question earnings quality and cash conversion. | E5: Operating cash flow ₹110 Cr; higher receivables and inventory. | F5: Cash-flow conversion expected to improve. | G5: Critical | H5: Prepare working-capital and cash-conversion explanation.
A6: 3 | B6: Segment Performance | C6: Why has Consumer Technology growth slowed and what gives investors confidence? | D6: Growth fell materially from the previous period. | E6: Growth ~7%; prior growth ~15%; selected consumer demand softened. | F6: Low double-digit growth expected. | G6: High | H6: Prepare segment demand response and recovery actions.
A7: 4 | B7: Guidance | C7: Last quarter management indicated margins would remain above 20%. What caused the miss? | D7: Actual performance differs from a clear prior commitment. | E7: Expected >20%; actual 18%; higher costs and mix pressure. | F7: Margin expected above 20%. | G7: High | H7: Directly acknowledge deviation and explain corrective actions.
A8: 5 | B8: Sustainability | C8: Is the current margin pressure temporary or should investors expect structurally lower profitability? | D8: Margin decline could be structural if cost/mix issues persist. | E8: Margin 18%; pricing, supplier and cost-efficiency actions initiated. | F8: No structural decline was previously expected. | G8: High | H8: Explain what is temporary versus structural using disclosed evidence.

Sheet Response Review
A1: Evidence-Backed Response Review
A3: Priority | B3: Investor Question | C3: Direct Answer | D3: Evidence | E3: Explanation | F3: Management Action | G3: Forward-Looking Context | H3: Evidence Sources | I3: Commitment Gap? | J3: Unsupported Claim? | K3: Evidence Support | L3: Directness | M3: Concern Coverage | N3: Consistency | O3: Clarity | P3: Overall Score | Q3: Review
A4: 1 | B4: Why did margins decline despite revenue growth? | C4: Margin declined primarily because of higher input costs and an unfavourable product mix, partly offset by pricing actions. | D4: Revenue +15%; margin 22%→18%; input/supplier costs ~+8%; lower-margin mix. | E4: Revenue growth was concentrated in lower-margin offerings while input costs increased. | F4: Pricing actions, supplier negotiations and cost-efficiency initiatives. | G4: Management expects pressure to moderate as disclosed actions are implemented, subject to market conditions. | H4: Quarterly results; management commentary; prior earnings call | I4: Yes | J4: No | K4: 4.5 | L4: 4.5 | M4: 4 | N4: 4 | O4: 4 | P4: =AVERAGE(K4:O4) -> 4.2 | Q4: =IF(P4>=4.5,"Strong",IF(P4>=3.5,"Good — refine","Needs major improvement")) -> Good — refine
A5: 2 | B5: Why did operating cash flow decline despite revenue growth? | C5: Operating cash flow weakened primarily because higher receivables and inventory absorbed cash during the quarter. | D5: Operating cash flow ₹110 Cr; receivables ₹320 Cr; inventory ₹190 Cr. | E5: Cash conversion weakened despite topline growth. | F5: Management is focusing on cash conversion and working-capital normalization. | G5: Timing of normalization depends on receivable collection and inventory movement. | H5: Financial data; management commentary | I5: Yes | J5: No | K5: 4.5 | L5: 4.5 | M5: 4.5 | N5: 4 | O5: 4 | P5: =AVERAGE(K5:O5) -> 4.3 | Q5: =IF(P5>=4.5,"Strong",IF(P5>=3.5,"Good — refine","Needs major improvement")) -> Good — refine
A6: 3 | B6: Why has Consumer Technology growth slowed? | C6: Consumer Technology growth slowed as demand softened in selected categories. | D6: Growth ~7%; prior growth ~15%. | E6: Selected consumer demand weakened, reducing the segment's growth rate. | F6: Management needs to address pricing, product and demand initiatives using disclosed plans. | G6: The disclosure does not provide a quantified recovery timetable. | H6: Segment data; management commentary | I6: Yes | J6: No | K6: 4 | L6: 4 | M6: 4 | N6: 4.5 | O6: 4 | P6: =AVERAGE(K6:O6) -> 4.1 | Q6: =IF(P6>=4.5,"Strong",IF(P6>=3.5,"Good — refine","Needs major improvement")) -> Good — refine
A7: 4 | B7: What caused the margin guidance miss? | C7: The margin fell below the previous >20% expectation because of higher input costs and an unfavourable mix. | D7: Previous commitment >20%; actual 18%. | E7: The response explicitly acknowledges the deviation. | F7: Pricing and cost-efficiency initiatives were initiated. | G7: No unsupported target should be given beyond disclosed expectations. | H7: Prior earnings call; current results; management commentary | I7: Yes | J7: No | K7: 5 | L7: 5 | M7: 5 | N7: 5 | O7: 4.5 | P7: =AVERAGE(K7:O7) -> 4.9 | Q7: =IF(P7>=4.5,"Strong",IF(P7>=3.5,"Good — refine","Needs major improvement")) -> Strong
A8: 5 | B8: Is current margin pressure temporary or structural? | C8: Current disclosures indicate identifiable cost and mix pressures, but they do not conclusively establish how quickly margins will normalize. | D8: Margin 18%; cost and mix drivers identified; actions initiated. | E8: Some drivers may be manageable, but the disclosure does not establish a guaranteed recovery. | F8: Continue pricing, supplier and cost actions. | G8: Avoid unsupported claims about permanent recovery. | H8: Management commentary; current results | I8: No | J8: No | K8: 4.5 | L8: 4 | M8: 4 | N8: 4.5 | O8: 4.5 | P8: =AVERAGE(K8:O8) -> 4.3 | Q8: =IF(P8>=4.5,"Strong",IF(P8>=3.5,"Good — refine","Needs major improvement")) -> Good — refine

Sheet Leadership Preparation
A1: Leadership Preparation Brief
A3: Priority | B3: Concern | C3: What Leadership Must Prepare | D3: Evidence | E3: Recommended Talking Point | F3: Risk
A4: 1 | B4: Margin Recovery Story | C4: Prepare a quantified explanation of input-cost and product-mix pressure, supported by disclosed pricing and supplier actions. | D4: Margin 22%→18%; input costs ~+8%; lower-margin mix. | E4: Acknowledge the miss, explain the drivers, then explain the actions already underway. | F4: Critical
A5: 2 | B5: Cash-Flow Improvement | C5: Prepare a clear explanation of receivables, inventory and normalization. | D5: Operating cash flow ₹110 Cr; receivables ₹320 Cr; inventory ₹190 Cr. | E5: Separate reported profitability from cash conversion and explain the working-capital movement. | F5: Critical
A6: 3 | B6: Guidance Credibility | C6: Explicitly acknowledge the previous >20% margin expectation and explain why it was not achieved. | D6: Previous guidance >20%; current margin 18%. | E6: Do not avoid the prior commitment; address the gap directly. | F6: High
A7: 4 | B7: Consumer Technology Action Plan | C7: Prepare a detailed explanation of softer demand and actions being taken to address the slowdown. | D7: Growth ~7% versus ~15% previously. | E7: Explain what management is seeing, what it is doing and what is not yet known. | F7: High

Sheet Dashboard
A1: Nexora Technologies Limited — Investor Readiness Engine
A2: Q2 FY25 | Identify tough questions. Prepare stronger answers.
A4: Revenue | C4: Operating Margin | E4: Operating Cash Flow | G4: Enterprise Solutions | I4: Consumer Technology | K4: Digital Services
A5: ='Quarterly Financials'!E4 -> 1150 | C5: ='Quarterly Financials'!E6 -> 0.18 | E5: ='Quarterly Financials'!E7 -> 110 | G5: ='Segment Data'!E4 -> 500 | I5: ='Segment Data'!E5 -> 389 | K5: ='Segment Data'!E6 -> 261
A6: +15% | C6: -4 pp | E6: vs Q4 FY24: -38.9% | G6: +20% | I6: +7% | K6: +3%
A8: Top Investor Concerns | H8: Selected Investor Question
A9: Rank | B9: Concern | C9: Score | D9: Risk | E9: Why It Matters | F9: Preparation | H9: Why did margins decline despite revenue growth?
A10: 1 | B10: Operating margin decline | C10: 19 | D10: Critical | E10: Revenue growth is not translating into profitability. | F10: Margin bridge + guidance acknowledgment | H10: Evidence | I10: Revenue +15%; margin 22%→18%; input costs ~+8%; lower-margin mix.
A11: 2 | B11: Cash-flow deterioration | C11: 18 | D11: Critical | E11: Weak cash conversion can challenge earnings quality. | F11: Working-capital explanation | H11: Previous commitment | I11: Operating margin expected above 20%.
A12: 3 | B12: Guidance miss (margin) | C12: 17 | D12: Critical | E12: Prior commitment was not achieved. | F12: Explain deviation | H12: Consistency check | I12: COMMITMENT GAP DETECTED — current margin is 18%.
A13: 4 | B13: Consumer Technology slowdown | C13: 14 | D13: High | E13: Demand weakness may affect future growth mix. | F13: Segment response plan | H13: Response score | I13: 4.2 / 5
A14: 5 | B14: Working-capital pressure | C14: 13 | D14: High | E14: Receivables and inventory absorbed cash. | F14: Cash conversion bridge | H14: Recommendation | I14: Prepare a quantified margin-recovery story and acknowledge the prior guidance miss.
A17: Leadership Preparation
A18: Priority | B18: Action | C18: Why
A19: 1 | B19: Margin Recovery Story | C19: Quantify input-cost and mix pressure; explain pricing and supplier actions.
A20: 2 | B20: Cash-Flow Improvement | C20: Explain receivables, inventory and the path toward normalization.
A21: 3 | B21: Guidance Credibility | C21: Directly acknowledge previous >20% margin guidance and explain the gap.
